jax_sph/__init__.py
jax_sph/case_setup.py
jax_sph/defaults.py
jax_sph/eos.py
jax_sph/integrator.py
jax_sph/io_state.py
jax_sph/jax_md/LICENSE_JAX_MD.txt
jax_sph/jax_md/README.md
jax_sph/jax_md/__init__.py
jax_sph/jax_md/dataclasses.py
jax_sph/jax_md/partition.py
jax_sph/jax_md/space.py
jax_sph/jax_md/util.py
jax_sph/kernel.py
jax_sph/partition.py
jax_sph/simulate.py
jax_sph/solver.py
jax_sph/utils.py
jax_sph/visualize.py
jax_sph-0.1.0.dist-info/LICENSE
jax_sph-0.1.0.dist-info/METADATA
jax_sph-0.1.0.dist-info/WHEEL
jax_sph-0.1.0.dist-info/RECORD
