Metadata-Version: 2.1
Name: jax-sph
Version: 0.1.0
Summary: JAX-SPH: Smoothed Particle Hydrodynamics in JAX
Home-page: https://jax-sph.readthedocs.io/
License: MIT
Author: Artur Toshev
Author-email: artur.toshev@tum.de
Maintainer: Artur Toshev
Maintainer-email: artur.toshev@tum.de
Requires-Python: >=3.9,<=3.11
Classifier: License :: OSI Approved :: MIT License
Classifier: Programming Language :: Python :: 3
Classifier: Programming Language :: Python :: 3.9
Classifier: Programming Language :: Python :: 3.10
Classifier: Programming Language :: Python :: 3.11
Requires-Dist: absl-py (>=2.1.0)
Requires-Dist: h5py (>=3.9.0)
Requires-Dist: jax[cpu] (==0.4.29)
Requires-Dist: jaxlib (==0.4.29)
Requires-Dist: jraph (>=0.0.6.dev0)
Requires-Dist: matscipy (>=0.8.0)
Requires-Dist: omegaconf (>=2.3.0)
Requires-Dist: pandas (>=2.1.4)
Requires-Dist: pyvista (>=0.42.2)
Project-URL: Documentation, https://jax-sph.readthedocs.io/
Project-URL: Repository, https://github.com/tumaer/jax-sph
